flowai/__init__.py
flowai/chat_manager.py
flowai/config_manager.py
flowai/docs/README.md
flowai/docs/commands.md
flowai/docs/creating-prompts.md
flowai/docs/image_generation.md
flowai/llm_connector.py
flowai/main.py
flowai/prompts/prompt-chat.txt
flowai/prompts/prompt-code-review.txt
flowai/prompts/prompt-commit-message.txt
flowai/prompts/prompt-help.txt
flowai/prompts/prompt-index.txt
flowai/prompts/prompt-pull-request.txt
glagos_flowai-0.6.1.1.dist-info/METADATA
glagos_flowai-0.6.1.1.dist-info/WHEEL
glagos_flowai-0.6.1.1.dist-info/entry_points.txt
glagos_flowai-0.6.1.1.dist-info/RECORD
