Metadata-Version: 2.1
Name: glagos-flowai
Version: 0.6.1.1
Summary: A Python CLI tool for streamlining development workflows with LLMs - commit messages, PR descriptions, code reviews and more
Author: Gabriel Lagos
Author-email: gabriel@glagos.com
Requires-Python: >=3.9,<3.14
Classifier: Programming Language :: Python :: 3
Classifier: Programming Language :: Python :: 3.9
Classifier: Programming Language :: Python :: 3.10
Classifier: Programming Language :: Python :: 3.11
Classifier: Programming Language :: Python :: 3.12
Requires-Dist: anthropic (>=0.42.0,<0.43.0)
Requires-Dist: click (>=7.1.1,<8.2.0)
Requires-Dist: google-genai (>=1.11.0,<2.0.0)
Requires-Dist: groq (>=0.22.0,<0.23.0)
Requires-Dist: litellm (>=1.66.3,<2.0.0)
Requires-Dist: markdown-it-py (>=3.0.0,<4.0.0)
Requires-Dist: openai (>=1.75.0,<2.0.0)
Requires-Dist: pillow (>=11.2.1,<12.0.0)
Requires-Dist: pyperclip (>=1.8.2,<2.0.0)
Requires-Dist: questionary (>=2.0.1,<3.0.0)
Requires-Dist: requests (>=2.31.0,<3.0.0)
Requires-Dist: rich (>=13.7.0,<14.0.0)
Requires-Dist: typer (>=0.9.0,<0.10.0)
